{"matchNumber":"1","session":true,"startTime":"","autonStartTime":"","scoreboard":{"totalScore":{"redAllianceScore":0,"blueAllianceScore":0,"redAllianceLinks":0,"blueAllianceLinks":0,"redAllianceAutonScore":0,"blueAllianceAutonScore":0,"redAllianceTelopScore":0,"blueAllianceTelopScore":0,"redCoopScore":0,"blueCoopScore":0,"blueChargingScore":0,"redChargingScore":0,"blueRankingPoints":1,"redRankingPoints":1},"team":{"scout":"Blue1","teamNumber":"Blue1","idx":1,"allianceColor":"blue","markerColor":{"red":255,"green":255,"blue":10,"alpha":1},"gameState":{"markerScore":0,"parkingScore":0,"parkingState":"","pregame":{"markerScore":0,"parkingScore":0,"parkingState":""}},"teleopScore":{},"autonScore":{},"connection":true,"docked":false,"mobile":false,"engaged":false,"gameStateScore":"{\"markerScore\":0,\"parkingScore\":0,\"parkingState\":\"\",\"pregame\":{\"markerScore\":0,\"parkingScore\":0,\"parkingState\":\"\"}}"},"autonScore":{},"teleopScore":{},"startTime":""},"gamePlay":{"blue":{"gameState":"pregame","teams":[{"scout":"Dhruv","teamNumber":"","idx":0,"allianceColor":"blue","markerColor":{"red":255,"green":168,"blue":20,"alpha":1},"gameState":[],"teleopScore":{},"autonScore":{},"connection":false,"docked":false,"mobile":false,"engaged":false},{"scout":"Aryan","teamNumber":"","idx":0,"allianceColor":"blue","markerColor":{"red":255,"green":208,"blue":107,"alpha":1},"gameState":[],"teleopScore":{},"autonScore":{},"connection":false,"docked":false,"mobile":false,"engaged":false},{"scout":"Riley","teamNumber":"","idx":0,"allianceColor":"blue","markerColor":{"red":170,"green":102,"blue":255,"alpha":1},"gameState":[],"teleopScore":{},"autonScore":{},"connection":false,"docked":false,"mobile":false,"engaged":false},{"scout":"Jackson","teamNumber":"","idx":0,"allianceColor":"blue","markerColor":{"red":102,"green":173,"blue":16,"alpha":1},"gameState":[],"teleopScore":{},"autonScore":{},"connection":false,"docked":false,"mobile":false,"engaged":false},{"scout":"Ean","teamNumber":"","idx":0,"allianceColor":"blue","markerColor":{"red":156,"green":7,"blue":255,"alpha":1},"gameState":[],"teleopScore":{},"autonScore":{},"connection":false,"docked":false,"mobile":false,"engaged":false},{"scout":"Richi","teamNumber":"","idx":0,"allianceColor":"blue","markerColor":{"red":255,"green":215,"blue":193,"alpha":1},"gameState":[],"teleopScore":{},"autonScore":{},"connection":false,"docked":false,"mobile":false,"engaged":false},{"scout":"Abishta","teamNumber":"","idx":0,"allianceColor":"blue","markerColor":{"red":81,"green":139,"blue":255,"alpha":1},"gameState":[],"teleopScore":{},"autonScore":{},"connection":false,"docked":false,"mobile":false,"engaged":false},{"scout":"Athindra","teamNumber":"","idx":0,"allianceColor":"blue","markerColor":{"red":12,"green":255,"blue":178,"alpha":1},"gameState":[],"teleopScore":{},"autonScore":{},"connection":false,"docked":false,"mobile":false,"engaged":false},{"scout":"Pranav","teamNumber":"","idx":0,"allianceColor":"blue","markerColor":{"red":255,"green":71,"blue":86,"alpha":1},"gameState":[],"teleopScore":{},"autonScore":{},"connection":false,"docked":false,"mobile":false,"engaged":false},{"scout":"Aaditeya","teamNumber":"","idx":0,"allianceColor":"blue","markerColor":{"red":223,"green":226,"blue":47,"alpha":1},"gameState":[],"teleopScore":{},"autonScore":{},"connection":false,"docked":false,"mobile":false,"engaged":false},{"scout":"Cody","teamNumber":"","idx":0,"allianceColor":"blue","markerColor":{"red":213,"green":163,"blue":255,"alpha":1},"gameState":[],"teleopScore":{},"autonScore":{},"connection":false,"docked":false,"mobile":false,"engaged":false},{"scout":"Minnah","teamNumber":"","idx":0,"allianceColor":"blue","markerColor":{"red":255,"green":255,"blue":10,"alpha":1},"gameState":[],"teleopScore":{},"autonScore":{},"connection":false,"docked":false,"mobile":false,"engaged":false},{"scout":"Blue1","teamNumber":"Blue1","idx":1,"allianceColor":"blue","markerColor":{"red":255,"green":255,"blue":10,"alpha":1},"gameState":{"markerScore":0,"parkingScore":0,"parkingState":"","pregame":{"markerScore":0,"parkingScore":0,"parkingState":""}},"teleopScore":{},"autonScore":{},"connection":true,"docked":false,"mobile":false,"engaged":false,"gameStateScore":"{\"markerScore\":0,\"parkingScore\":0,\"parkingState\":\"\",\"pregame\":{\"markerScore\":0,\"parkingScore\":0,\"parkingState\":\"\"}}"},{"scout":"Blue2","teamNumber":"","idx":0,"allianceColor":"blue","markerColor":{"red":223,"green":226,"blue":47,"alpha":1},"gameState":[],"teleopScore":{},"autonScore":{},"connection":false,"docked":false,"mobile":false,"engaged":false},{"scout":"Blue3","teamNumber":"","idx":0,"allianceColor":"blue","markerColor":{"red":213,"green":163,"blue":255,"alpha":1},"gameState":[],"teleopScore":{},"autonScore":{},"connection":false,"docked":false,"mobile":false,"engaged":false},{"scout":"admin","teamNumber":"","idx":0,"allianceColor":"blue","markerColor":{"red":25,"green":25,"blue":25,"alpha":1},"gameState":[],"teleopScore":{},"autonScore":{},"connection":false,"docked":false,"mobile":false,"engaged":false}],"autonMarkers":{},"telopMarkers":{},"preGameMarkers":{},"links":[],"chargingStation":{"x":7,"y":5,"width":4,"height":5,"docked":0,"engaged":0,"level":false},"parkingField":{"rectOne_x":3,"rectOne_y":3,"rectOne_width":4,"rectOne_height":7,"rectTwo_x":3,"rectTwo_y":9,"rectTwo_width":7,"rectTwo_height":2},"itemField":{"x":0,"y":3,"width":3,"height":9},"idx":1},"red":{"gameState":"pregame","teams":[{"scout":"Aaradhya","teamNumber":"","idx":0,"allianceColor":"red","markerColor":{"red":176,"green":11,"blue":222,"alpha":1},"gameState":[],"teleopScore":{},"autonScore":{},"connection":false,"docked":false,"mobile":false,"engaged":false},{"scout":"Karun","teamNumber":"","idx":0,"allianceColor":"red","markerColor":{"red":66,"green":230,"blue":21,"alpha":1},"gameState":[],"teleopScore":{},"autonScore":{},"connection":false,"docked":false,"mobile":false,"engaged":false},{"scout":"Brennan","teamNumber":"","idx":0,"allianceColor":"red","markerColor":{"red":214,"green":17,"blue":129,"alpha":1},"gameState":[],"teleopScore":{},"autonScore":{},"connection":false,"docked":false,"mobile":false,"engaged":false},{"scout":"Michael","teamNumber":"","idx":0,"allianceColor":"red","markerColor":{"red":226,"green":73,"blue":22,"alpha":1},"gameState":[],"teleopScore":{},"autonScore":{},"connection":false,"docked":false,"mobile":false,"engaged":false},{"scout":"Erin","teamNumber":"","idx":0,"allianceColor":"red","markerColor":{"red":176,"green":11,"blue":222,"alpha":1},"gameState":[],"teleopScore":{},"autonScore":{},"connection":false,"docked":false,"mobile":false,"engaged":false},{"scout":"Nandika","teamNumber":"","idx":0,"allianceColor":"red","markerColor":{"red":82,"green":229,"blue":219,"alpha":1},"gameState":[],"teleopScore":{},"autonScore":{},"connection":false,"docked":false,"mobile":false,"engaged":false},{"scout":"Shaurya","teamNumber":"","idx":0,"allianceColor":"red","markerColor":{"red":69,"green":10,"blue":16,"alpha":1},"gameState":[],"teleopScore":{},"autonScore":{},"connection":false,"docked":false,"mobile":false,"engaged":false},{"scout":"Anshul B","teamNumber":"","idx":0,"allianceColor":"red","markerColor":{"red":183,"green":255,"blue":216,"alpha":1},"gameState":[],"teleopScore":{},"autonScore":{},"connection":false,"docked":false,"mobile":false,"engaged":false},{"scout":"Anshul","teamNumber":"","idx":0,"allianceColor":"red","markerColor":{"red":145,"green":255,"blue":203,"alpha":1},"gameState":[],"teleopScore":{},"autonScore":{},"connection":false,"docked":false,"mobile":false,"engaged":false},{"scout":"Aryaman","teamNumber":"","idx":0,"allianceColor":"red","markerColor":{"red":255,"green":163,"blue":153,"alpha":1},"gameState":[],"teleopScore":{},"autonScore":{},"connection":false,"docked":false,"mobile":false,"engaged":false},{"scout":"Nisha","teamNumber":"","idx":0,"allianceColor":"red","markerColor":{"red":122,"green":252,"blue":255,"alpha":1},"gameState":[],"teleopScore":{},"autonScore":{},"connection":false,"docked":false,"mobile":false,"engaged":false},{"scout":"Abhi","teamNumber":"","idx":0,"allianceColor":"red","markerColor":{"red":83,"green":55,"blue":117,"alpha":1},"gameState":[],"teleopScore":{},"autonScore":{},"connection":false,"docked":false,"mobile":false,"engaged":false},{"scout":"Ramesh","teamNumber":"","idx":0,"allianceColor":"red","markerColor":{"red":178,"green":137,"blue":255,"alpha":1},"gameState":[],"teleopScore":{},"autonScore":{},"connection":false,"docked":false,"mobile":false,"engaged":false},{"scout":"Red1","teamNumber":"Red1","idx":4,"allianceColor":"red","markerColor":{"red":122,"green":252,"blue":255,"alpha":1},"gameState":{"markerScore":0,"parkingScore":0,"parkingState":""},"teleopScore":{},"autonScore":{},"connection":false,"docked":false,"mobile":false,"engaged":false},{"scout":"Red2","teamNumber":"","idx":0,"allianceColor":"red","markerColor":{"red":83,"green":55,"blue":117,"alpha":1},"gameState":[],"teleopScore":{},"autonScore":{},"connection":false,"docked":false,"mobile":false,"engaged":false},{"scout":"Red3","teamNumber":"","idx":0,"allianceColor":"red","markerColor":{"red":178,"green":137,"blue":255,"alpha":1},"gameState":[],"teleopScore":{},"autonScore":{},"connection":false,"docked":false,"mobile":false,"engaged":false},{"scout":"admin","teamNumber":"","idx":0,"allianceColor":"red","markerColor":{"red":25,"green":25,"blue":25,"alpha":1},"gameState":[],"teleopScore":{},"autonScore":{},"connection":false,"docked":false,"mobile":false,"engaged":false}],"autonMarkers":{},"telopMarkers":{},"preGameMarkers":{},"links":[],"chargingStation":{"x":4,"y":5,"width":3,"height":5,"docked":0,"engaged":0,"level":false},"parkingField":{"rectOne_x":7,"rectOne_y":3,"rectOne_width":4,"rectOne_height":7,"rectTwo_x":4,"rectTwo_y":10,"rectTwo_width":7,"rectTwo_height":2},"itemField":{"x":11,"y":3,"width":3,"height":9},"idx":1}},"admin":true}