{
    "blue": [
        {
            "name": "Scott",
            "color": {
                "red": "235",
                "green": "255",
                "blue": "137"
            }
        },
        {
            "name": "blue2",
            "color": {
                "red": "90",
                "green": "235",
                "blue": "50"
            }
        },
        {
            "name": "blue3",
            "color": {
                "red": "235",
                "green": "135",
                "blue": "50"
            }
        },
        {
            "name": "blue4",
            "color": {
                "red": "65",
                "green": "135",
                "blue": "200"
            }
        }
    ],
    "red": [
        {
            "name": "Sterling",
            "color": {
                "red": "245",
                "green": "255",
                "blue": "137"
            }
        },
        {
            "name": "David",
            "color": {
                "red": "90",
                "green": "245",
                "blue": "50"
            }
        },
        {
            "name": "red3",
            "color": {
                "red": "",
                "green": "",
                "blue": ""
            }
        },
        {
            "name": "red4",
            "color": {
                "red": "",
                "green": "",
                "blue": ""
            }
        }
    ]
}