{"matchNumber":"53","startTime":152.07213820600043,"scoreboard":{"totalScore":{"redAllianceScore":57,"blueAllianceScore":87,"redAllianceLinks":0,"blueAllianceLinks":2,"redAllianceAutonScore":15,"blueAllianceAutonScore":21,"redAllianceTelopScore":42,"blueAllianceTelopScore":66,"redCoopScore":4,"blueCoopScore":5,"blueChargingScore":28,"redChargingScore":28,"blueRankingPoints":3,"redRankingPoints":1},"team":{"scout":"Kunal","teamNumber":"6526","idx":5,"allianceColor":"red","markerColor":{"red":221,"green":160,"blue":221,"alpha":0.3},"gameState":[],"teleopScore":{"markerScore":6,"parkingScore":2,"parkingState":"Parked"},"autonScore":{"markerScore":0,"parkingScore":3,"parkingState":"Parked"},"connection":true,"docked":false,"engaged":false,"gameStateScore":"[]"},"autonScore":{"markerScore":0,"parkingScore":3,"parkingState":"Parked"},"teleopScore":{"markerScore":6,"parkingScore":2,"parkingState":"Parked"},"startTime":152.07213820600043},"gamePlay":{"blue":{"scoreBoard":{"redAllianceScore":0,"blueAllianceScore":0,"redAllianceLinks":0,"blueAllianceLinks":0,"redAllianceAutonScore":0,"blueAllianceAutonScore":0,"redAllianceTelopScore":0,"blueAllianceTelopScore":0,"redCoopScore":0,"blueCoopScore":0},"gameState":"teleop","teams":[{"scout":"Puranjay","teamNumber":"9128","idx":3,"allianceColor":"blue","markerColor":{"red":235,"green":255,"blue":137,"alpha":0.3},"gameState":[],"teleopScore":{"markerScore":28,"parkingScore":10,"parkingState":"Engaged"},"autonScore":{"markerScore":3,"parkingScore":3,"parkingState":"Parked"},"connection":true,"docked":false,"engaged":false,"gameStateScore":"[]"},{"scout":"Sahasra","teamNumber":"","idx":0,"allianceColor":"blue","markerColor":{"red":90,"green":235,"blue":50,"alpha":1},"gameState":[],"teleopScore":{},"autonScore":{},"connection":false,"docked":false,"engaged":false},{"scout":"Pranav","teamNumber":"7503","idx":2,"allianceColor":"blue","markerColor":{"red":235,"green":135,"blue":50,"alpha":0.3},"gameState":[],"teleopScore":{"markerScore":18,"parkingScore":6,"parkingState":"Docked"},"autonScore":{"markerScore":3,"parkingScore":12,"parkingState":"Engaged"},"connection":true,"docked":false,"engaged":true,"gameStateScore":"[]"},{"scout":"Anshul","teamNumber":"8816","idx":1,"allianceColor":"blue","markerColor":{"red":65,"green":135,"blue":200,"alpha":0.3},"gameState":[],"teleopScore":{"markerScore":2,"parkingScore":2,"parkingState":"Parked"},"autonScore":{"markerScore":0,"parkingScore":0,"parkingState":""},"connection":true,"docked":false,"engaged":false,"gameStateScore":"[]"},{"scout":"admin","teamNumber":"","idx":0,"allianceColor":"blue","markerColor":{"red":25,"green":25,"blue":25,"alpha":0.5},"gameState":[],"teleopScore":{},"autonScore":{},"connection":false,"docked":false,"engaged":false,"gameStateScore":"[]"}],"autonMarkers":{"x2y7":{"x":2,"y":7,"gameState":"auton","teamNumber":"7503","timestamp":4.30568575700002,"score":3,"markerColor":{"red":235,"green":135,"blue":50,"alpha":0.7},"markerType":"Item"},"x2y3":{"x":2,"y":3,"gameState":"auton","teamNumber":"9128","timestamp":5.893090477999294,"score":3,"markerColor":{"red":235,"green":255,"blue":137,"alpha":0.7},"markerType":"Item"},"x8y4":{"x":8,"y":4,"gameState":"auton","teamNumber":"9128","timestamp":9.099621012999677,"score":3,"markerColor":{"red":235,"green":255,"blue":137,"alpha":0.7},"markerType":"AutonParked"},"x8y6":{"x":8,"y":6,"gameState":"auton","teamNumber":"7503","timestamp":null,"score":12,"markerColor":{"red":235,"green":135,"blue":50,"alpha":1.4},"markerType":"Engaged"}},"telopMarkers":{"x8y7":{"x":8,"y":7,"gameState":"teleop","teamNumber":"7503","timestamp":null,"score":6,"markerColor":{"red":235,"green":135,"blue":50,"alpha":0.6},"markerType":"Docked"},"x1y7":{"x":1,"y":7,"gameState":"teleop","teamNumber":"9128","timestamp":41.41132838299964,"score":3,"markerColor":{"red":235,"green":255,"blue":137,"alpha":0.3},"markerType":"Item"},"x0y4":{"x":0,"y":4,"gameState":"teleop","teamNumber":"7503","timestamp":42.03408899299987,"score":5,"markerColor":{"red":235,"green":135,"blue":50,"alpha":0.3},"markerType":"Item"},"x0y7":{"x":0,"y":7,"gameState":"teleop","teamNumber":"9128","timestamp":57.929963872999906,"score":5,"markerColor":{"red":235,"green":255,"blue":137,"alpha":0.3},"markerType":"Item"},"x1y4":{"x":1,"y":4,"gameState":"teleop","teamNumber":"7503","timestamp":73.74648614099996,"score":3,"markerColor":{"red":235,"green":135,"blue":50,"alpha":0.3},"markerType":"Item"},"x0y9":{"x":0,"y":9,"gameState":"teleop","teamNumber":"9128","timestamp":78.39678595299927,"score":5,"markerColor":{"red":235,"green":255,"blue":137,"alpha":0.3},"markerType":"Item"},"x0y8":{"x":0,"y":8,"gameState":"teleop","teamNumber":"9128","timestamp":98.85600801499933,"score":5,"markerColor":{"red":235,"green":255,"blue":137,"alpha":0.3},"markerType":"Item"},"x0y5":{"x":0,"y":5,"gameState":"teleop","teamNumber":"7503","timestamp":107.20671052899957,"score":5,"markerColor":{"red":235,"green":135,"blue":50,"alpha":0.3},"markerType":"Item"},"x0y6":{"x":0,"y":6,"gameState":"teleop","teamNumber":"9128","timestamp":123.64026331499963,"score":5,"markerColor":{"red":235,"green":255,"blue":137,"alpha":0.3},"markerType":"Item"},"x0y10":{"x":0,"y":10,"gameState":"teleop","teamNumber":"9128","timestamp":139.72052473099995,"score":5,"markerColor":{"red":235,"green":255,"blue":137,"alpha":0.3},"markerType":"Item"},"x0y3":{"x":0,"y":3,"gameState":"teleop","teamNumber":"7503","timestamp":139.76563063899988,"score":5,"markerColor":{"red":235,"green":135,"blue":50,"alpha":0.3},"markerType":"Item"},"x2y10":{"x":2,"y":10,"gameState":"teleop","teamNumber":"8816","timestamp":148.62943504099923,"score":2,"markerColor":{"red":65,"green":135,"blue":200,"alpha":0.3},"markerType":"Item"},"x8y8":{"x":8,"y":8,"gameState":"teleop","teamNumber":"9128","timestamp":null,"score":10,"markerColor":{"red":235,"green":255,"blue":137,"alpha":0.6},"markerType":"Engaged"},"x5y10":{"x":5,"y":10,"gameState":"teleop","teamNumber":"8816","timestamp":209.9970110229999,"score":2,"markerColor":{"red":65,"green":135,"blue":200,"alpha":0.3},"markerType":"Parked"}},"preGameMarkers":{"x3y11":{"x":3,"y":11,"gameState":"pregame","teamNumber":"8816","timestamp":"","score":0,"markerColor":{"red":65,"green":135,"blue":200,"alpha":1},"markerType":"Item"}},"links":[],"chargingStation":{"x":7,"y":5,"width":4,"height":5,"docked":0,"engaged":1,"level":false},"parkingField":{"rectOne_x":3,"rectOne_y":3,"rectOne_width":4,"rectOne_height":7,"rectTwo_x":3,"rectTwo_y":9,"rectTwo_width":7,"rectTwo_height":2},"itemField":{"x":0,"y":3,"width":3,"height":9}},"red":{"scoreBoard":{"redAllianceScore":0,"blueAllianceScore":0,"redAllianceLinks":0,"blueAllianceLinks":0,"redAllianceAutonScore":0,"blueAllianceAutonScore":0,"redAllianceTelopScore":0,"blueAllianceTelopScore":0,"redCoopScore":0,"blueCoopScore":0},"gameState":"teleop","teams":[{"scout":"Fatemeh","teamNumber":"9156","idx":4,"allianceColor":"red","markerColor":{"red":245,"green":255,"blue":137,"alpha":0.3},"gameState":[],"teleopScore":{"markerScore":10,"parkingScore":10,"parkingState":"Engaged"},"autonScore":{"markerScore":0,"parkingScore":12,"parkingState":"Engaged"},"connection":true,"docked":false,"engaged":false,"gameStateScore":"[]"},{"scout":"Rithvik","teamNumber":"","idx":0,"allianceColor":"red","markerColor":{"red":90,"green":245,"blue":50,"alpha":1},"gameState":[],"teleopScore":{},"autonScore":{},"connection":false,"docked":false,"engaged":false},{"scout":"Cody","teamNumber":"9080","idx":6,"allianceColor":"red","markerColor":{"red":94,"green":97,"blue":255,"alpha":0.7},"gameState":[],"teleopScore":{"markerScore":8,"parkingScore":6,"parkingState":"Docked"},"autonScore":{"markerScore":0,"parkingScore":0,"parkingState":""},"connection":true,"docked":false,"engaged":false,"gameStateScore":"[]"},{"scout":"Kunal","teamNumber":"6526","idx":5,"allianceColor":"red","markerColor":{"red":221,"green":160,"blue":221,"alpha":0.3},"gameState":[],"teleopScore":{"markerScore":6,"parkingScore":2,"parkingState":"Parked"},"autonScore":{"markerScore":0,"parkingScore":3,"parkingState":"Parked"},"connection":true,"docked":false,"engaged":false,"gameStateScore":"[]"},{"scout":"admin","teamNumber":"","idx":0,"allianceColor":"red","markerColor":{"red":25,"green":25,"blue":25,"alpha":0.5},"gameState":[],"teleopScore":{},"autonScore":{},"connection":false,"docked":false,"engaged":false,"gameStateScore":"[]"}],"autonMarkers":{"x3y3":{"x":3,"y":3,"gameState":"auton","teamNumber":"6526","timestamp":7.112058939999912,"score":3,"markerColor":{"red":221,"green":160,"blue":221,"alpha":0.7},"markerType":"AutonParked"},"x5y8":{"x":5,"y":8,"gameState":"auton","teamNumber":"9156","timestamp":null,"score":12,"markerColor":{"red":245,"green":255,"blue":137,"alpha":1.4},"markerType":"Engaged"}},"telopMarkers":{"x13y10":{"x":13,"y":10,"gameState":"teleop","teamNumber":"9080","timestamp":29.458730518999516,"score":5,"markerColor":{"red":94,"green":97,"blue":255,"alpha":0.3},"markerType":"Item"},"x11y5":{"x":11,"y":5,"gameState":"teleop","teamNumber":"6526","timestamp":45.347362046999876,"score":2,"markerColor":{"red":221,"green":160,"blue":221,"alpha":0.3},"markerType":"Item"},"x12y7":{"x":12,"y":7,"gameState":"teleop","teamNumber":"9080","timestamp":72.17176560499985,"score":3,"markerColor":{"red":94,"green":97,"blue":255,"alpha":0.3},"markerType":"Item"},"x11y4":{"x":11,"y":4,"gameState":"teleop","teamNumber":"6526","timestamp":91.4155104080001,"score":2,"markerColor":{"red":221,"green":160,"blue":221,"alpha":0.3},"markerType":"Item"},"x13y6":{"x":13,"y":6,"gameState":"teleop","teamNumber":"9156","timestamp":100.34589166199976,"score":5,"markerColor":{"red":245,"green":255,"blue":137,"alpha":0.3},"markerType":"Item"},"x12y8":{"x":12,"y":8,"gameState":"teleop","teamNumber":"9156","timestamp":138.9369748239992,"score":3,"markerColor":{"red":245,"green":255,"blue":137,"alpha":0.3},"markerType":"Item"},"x11y3":{"x":11,"y":3,"gameState":"teleop","teamNumber":"6526","timestamp":141.96307528600005,"score":2,"markerColor":{"red":221,"green":160,"blue":221,"alpha":0.3},"markerType":"Item"},"x5y6":{"x":5,"y":6,"gameState":"auton","teamNumber":"9080","timestamp":null,"score":6,"markerColor":{"red":94,"green":97,"blue":255,"alpha":1.4},"markerType":"Docked"},"x9y4":{"x":9,"y":4,"gameState":"teleop","teamNumber":"6526","timestamp":151.42885183599964,"score":2,"markerColor":{"red":221,"green":160,"blue":221,"alpha":0.3},"markerType":"Parked"},"x6y8":{"x":6,"y":8,"gameState":"teleop","teamNumber":"9156","timestamp":null,"score":10,"markerColor":{"red":245,"green":255,"blue":137,"alpha":0.6},"markerType":"Engaged"},"x11y6":{"x":11,"y":6,"gameState":"teleop","teamNumber":"9156","timestamp":184.51862774199992,"score":2,"markerColor":{"red":245,"green":255,"blue":137,"alpha":0.3},"markerType":"Item"}},"preGameMarkers":{"x10y4":{"x":10,"y":4,"gameState":"pregame","teamNumber":"6526","timestamp":"","score":0,"markerColor":{"red":221,"green":160,"blue":221,"alpha":1},"markerType":"Parked"},"x10y8":{"x":10,"y":8,"gameState":"pregame","teamNumber":"9156","timestamp":"","score":0,"markerColor":{"red":245,"green":255,"blue":137,"alpha":1},"markerType":"Parked"},"x10y10":{"x":10,"y":10,"gameState":"pregame","teamNumber":"9080","timestamp":"","score":0,"markerColor":{"red":94,"green":97,"blue":255,"alpha":1},"markerType":"Parked"}},"links":[],"chargingStation":{"x":4,"y":5,"width":3,"height":5,"docked":0,"engaged":0,"level":false},"parkingField":{"rectOne_x":7,"rectOne_y":3,"rectOne_width":4,"rectOne_height":7,"rectTwo_x":4,"rectTwo_y":10,"rectTwo_width":7,"rectTwo_height":2},"itemField":{"x":11,"y":3,"width":3,"height":9}}},"admin":true}